cableloss.py
cableloss-0.2.1.dist-info/AUTHORS.md
cableloss-0.2.1.dist-info/LICENSE.txt
cableloss-0.2.1.dist-info/METADATA
cableloss-0.2.1.dist-info/WHEEL
cableloss-0.2.1.dist-info/top_level.txt
cableloss-0.2.1.dist-info/RECORD
