Metadata-Version: 2.1
Name: cableloss
Version: 0.2.1
Summary: Calculate cable loss based on cable type and length
Home-page: http://github.com/questrail/cableloss
Author: Matthew Rankin
Author-email: matthew@questrail.com
License: MIT
Classifier: Programming Language :: Python
Classifier: Programming Language :: Python :: 3
Classifier: Programming Language :: Python :: 3.5
Classifier: Programming Language :: Python :: 3.6
Classifier: Programming Language :: Python :: 3.7
Classifier: Programming Language :: Python :: 3.8
Classifier: Programming Language :: Python :: 3.9
Classifier: License :: OSI Approved :: MIT License
Classifier: Development Status :: 3 - Alpha
Classifier: Operating System :: OS Independent
Classifier: Intended Audience :: Developers
Classifier: Topic :: Software Development :: Libraries :: Python Modules
Requires: numpy (>=1.22.0)
License-File: LICENSE.txt
License-File: AUTHORS.md
